crownstone_sse/__init__.py
crownstone_sse/async_client.py
crownstone_sse/client.py
crownstone_sse/const.py
crownstone_sse/events.py
crownstone_sse/exceptions.py
crownstone_sse/helpers/__init__.py
crownstone_sse/helpers/aiohttp_client.py
crownstone_sse/helpers/switch_command.py
crownstone_sse/util/__init__.py
crownstone_sse/util/eventbus.py
crownstone_sse-2.0.5.dist-info/LICENSE-APACHE
crownstone_sse-2.0.5.dist-info/LICENSE-LGPL
crownstone_sse-2.0.5.dist-info/LICENSE-MIT
crownstone_sse-2.0.5.dist-info/METADATA
crownstone_sse-2.0.5.dist-info/WHEEL
crownstone_sse-2.0.5.dist-info/top_level.txt
crownstone_sse-2.0.5.dist-info/RECORD
