Metadata-Version: 2.1
Name: crownstone-sse
Version: 2.0.5
Home-page: https://github.com/Crownstone-Community/crownstone-lib-python-sse
Author: Crownstone B.V.
Classifier: Programming Language :: Python :: 3.8
Classifier: Programming Language :: Python :: 3.9
Classifier: Programming Language :: Python :: 3.10
Classifier: Programming Language :: Python :: 3.11
Classifier: Programming Language :: Python :: 3.12
Requires-Python: >=3.8
License-File: LICENSE-APACHE
License-File: LICENSE-LGPL
License-File: LICENSE-MIT
Requires-Dist: aiohttp~=3.7
Requires-Dist: certifi
